mcp_server_as/__init__.py
mcp_server_as/client.py
mcp_server_as/server.py
mcp_server_as/tool_as.py
mcp_server_as-0.1.1.dist-info/METADATA
mcp_server_as-0.1.1.dist-info/WHEEL
mcp_server_as-0.1.1.dist-info/entry_points.txt
mcp_server_as-0.1.1.dist-info/RECORD
