Metadata-Version: 2.4
Name: mcp-server-as
Version: 0.1.1
Summary: MCP Server for Tencent Cloud Autoscaling
Requires-Python: >=3.10
Requires-Dist: mcp>=1.0.0
Requires-Dist: tencentcloud-sdk-python-autoscaling>=3.0.1361
Requires-Dist: tencentcloud-sdk-python-common>=3.0.1361
